[
  {
    "id": "local_test_1770898418@example.com_20260212_121338",
    "email": "local_test_1770898418@example.com",
    "phone": "9998887777",
    "age": 34,
    "gender": "Male",
    "occupation": "Engineer",
    "stress": 6,
    "bp": "120/80",
    "heart_rate": 72,
    "sleep_duration": 5.5,
    "bmi": "Normal",
    "snoring": "Never",
    "work_hours": 9,
    "diagnosis": "Sleep Deprivation",
    "full_diagnosis": "Moderate Risk: Sleep Deprivation",
    "prediction": 1,
    "severity_color": "orange",
    "timestamp": "2026-02-12T12:13:38.582467"
  },
  {
    "id": "local_test_1770898418@example.com_20260212_121339",
    "email": "local_test_1770898418@example.com",
    "phone": "9998887777",
    "age": 30,
    "gender": "Male",
    "occupation": "Tester",
    "stress": 2,
    "bp": "110/70",
    "heart_rate": 65,
    "sleep_duration": 8.0,
    "bmi": "Normal",
    "snoring": "Never",
    "work_hours": 8,
    "diagnosis": "Normal",
    "full_diagnosis": "No sleep disorder detected",
    "prediction": 0,
    "severity_color": "green",
    "timestamp": "2026-02-12T12:13:39.878913"
  },
  {
    "id": "local_test_1770898418@example.com_20260212_121339",
    "email": "local_test_1770898418@example.com",
    "phone": "9998887777",
    "age": 45,
    "gender": "Male",
    "occupation": "Tester",
    "stress": 9,
    "bp": "140/90",
    "heart_rate": 95,
    "sleep_duration": 3.5,
    "bmi": "Obese",
    "snoring": "Every Night",
    "work_hours": 12,
    "diagnosis": "Sleep Apnea",
    "full_diagnosis": "Critical Risk: Possible Sleep Apnea",
    "prediction": 3,
    "severity_color": "darkred",
    "timestamp": "2026-02-12T12:13:39.915217"
  },
  {
    "id": "local_test_1770898771@example.com_20260212_121932",
    "email": "local_test_1770898771@example.com",
    "phone": "9998887777",
    "age": 34,
    "gender": "Male",
    "occupation": "Engineer",
    "stress": 6,
    "bp": "120/80",
    "heart_rate": 72,
    "sleep_duration": 5.5,
    "bmi": "Normal",
    "snoring": "Never",
    "work_hours": 9,
    "diagnosis": "Sleep Deprivation",
    "full_diagnosis": "Moderate Risk: Sleep Deprivation",
    "prediction": 1,
    "severity_color": "orange",
    "timestamp": "2026-02-12T12:19:32.037376"
  },
  {
    "id": "local_test_1770898771@example.com_20260212_121932",
    "email": "local_test_1770898771@example.com",
    "phone": "9998887777",
    "age": 30,
    "gender": "Male",
    "occupation": "Tester",
    "stress": 2,
    "bp": "110/70",
    "heart_rate": 65,
    "sleep_duration": 8.0,
    "bmi": "Normal",
    "snoring": "Never",
    "work_hours": 8,
    "diagnosis": "Normal",
    "full_diagnosis": "No sleep disorder detected",
    "prediction": 0,
    "severity_color": "green",
    "timestamp": "2026-02-12T12:19:32.649483"
  },
  {
    "id": "local_test_1770898771@example.com_20260212_121932",
    "email": "local_test_1770898771@example.com",
    "phone": "9998887777",
    "age": 45,
    "gender": "Male",
    "occupation": "Tester",
    "stress": 9,
    "bp": "140/90",
    "heart_rate": 95,
    "sleep_duration": 3.5,
    "bmi": "Obese",
    "snoring": "Every Night",
    "work_hours": 12,
    "diagnosis": "Sleep Apnea",
    "full_diagnosis": "Critical Risk: Possible Sleep Apnea",
    "prediction": 3,
    "severity_color": "darkred",
    "timestamp": "2026-02-12T12:19:32.684398"
  },
  {
    "id": "local_test_1770899120@example.com_20260212_122520",
    "email": "local_test_1770899120@example.com",
    "phone": "9998887777",
    "age": 34,
    "gender": "Male",
    "occupation": "Engineer",
    "stress": 6,
    "bp": "120/80",
    "heart_rate": 72,
    "sleep_duration": 5.5,
    "bmi": "Normal",
    "snoring": "Never",
    "work_hours": 9,
    "diagnosis": "Sleep Deprivation",
    "full_diagnosis": "Moderate Risk: Sleep Deprivation",
    "prediction": 1,
    "severity_color": "orange",
    "timestamp": "2026-02-12T12:25:20.545361"
  },
  {
    "id": "local_test_1770899120@example.com_20260212_122520",
    "email": "local_test_1770899120@example.com",
    "phone": "9998887777",
    "age": 30,
    "gender": "Male",
    "occupation": "Tester",
    "stress": 2,
    "bp": "110/70",
    "heart_rate": 65,
    "sleep_duration": 8.0,
    "bmi": "Normal",
    "snoring": "Never",
    "work_hours": 8,
    "diagnosis": "Normal",
    "full_diagnosis": "No sleep disorder detected",
    "prediction": 0,
    "severity_color": "green",
    "timestamp": "2026-02-12T12:25:20.729086"
  },
  {
    "id": "local_test_1770899120@example.com_20260212_122520",
    "email": "local_test_1770899120@example.com",
    "phone": "9998887777",
    "age": 45,
    "gender": "Male",
    "occupation": "Tester",
    "stress": 9,
    "bp": "140/90",
    "heart_rate": 95,
    "sleep_duration": 3.5,
    "bmi": "Obese",
    "snoring": "Every Night",
    "work_hours": 12,
    "diagnosis": "Sleep Apnea",
    "full_diagnosis": "Critical Risk: Possible Sleep Apnea",
    "prediction": 3,
    "severity_color": "darkred",
    "timestamp": "2026-02-12T12:25:20.764322"
  }
]